crispy_bootstrap5/__init__.py
crispy_bootstrap5/bootstrap5.py
crispy_bootstrap5/templates/bootstrap5/accordion-group.html
crispy_bootstrap5/templates/bootstrap5/accordion.html
crispy_bootstrap5/templates/bootstrap5/betterform.html
crispy_bootstrap5/templates/bootstrap5/display_form.html
crispy_bootstrap5/templates/bootstrap5/errors.html
crispy_bootstrap5/templates/bootstrap5/errors_formset.html
crispy_bootstrap5/templates/bootstrap5/field.html
crispy_bootstrap5/templates/bootstrap5/inputs.html
crispy_bootstrap5/templates/bootstrap5/table_inline_formset.html
crispy_bootstrap5/templates/bootstrap5/uni_form.html
crispy_bootstrap5/templates/bootstrap5/uni_formset.html
crispy_bootstrap5/templates/bootstrap5/whole_uni_form.html
crispy_bootstrap5/templates/bootstrap5/whole_uni_formset.html
crispy_bootstrap5/templates/bootstrap5/layout/alert.html
crispy_bootstrap5/templates/bootstrap5/layout/attrs.html
crispy_bootstrap5/templates/bootstrap5/layout/baseinput.html
crispy_bootstrap5/templates/bootstrap5/layout/button.html
crispy_bootstrap5/templates/bootstrap5/layout/buttonholder.html
crispy_bootstrap5/templates/bootstrap5/layout/checkboxselectmultiple_inline.html
crispy_bootstrap5/templates/bootstrap5/layout/column.html
crispy_bootstrap5/templates/bootstrap5/layout/div.html
crispy_bootstrap5/templates/bootstrap5/layout/field_errors.html
crispy_bootstrap5/templates/bootstrap5/layout/field_errors_block.html
crispy_bootstrap5/templates/bootstrap5/layout/field_file.html
crispy_bootstrap5/templates/bootstrap5/layout/field_with_buttons.html
crispy_bootstrap5/templates/bootstrap5/layout/fieldset.html
crispy_bootstrap5/templates/bootstrap5/layout/floating_field.html
crispy_bootstrap5/templates/bootstrap5/layout/formactions.html
crispy_bootstrap5/templates/bootstrap5/layout/help_text.html
crispy_bootstrap5/templates/bootstrap5/layout/help_text_and_errors.html
crispy_bootstrap5/templates/bootstrap5/layout/inline_field.html
crispy_bootstrap5/templates/bootstrap5/layout/modal.html
crispy_bootstrap5-2024.10.dist-info/LICENSE
crispy_bootstrap5-2024.10.dist-info/METADATA
crispy_bootstrap5-2024.10.dist-info/WHEEL
crispy_bootstrap5-2024.10.dist-info/top_level.txt
crispy_bootstrap5-2024.10.dist-info/RECORD
