Metadata-Version: 2.1
Name: crispy-bootstrap5
Version: 2024.10
Summary: Bootstrap5 template pack for django-crispy-forms
Author: David Smith
License: MIT
Project-URL: CI, https://github.com/django-crispy-forms/crispy-bootstrap5/actions
Project-URL: Changelog, https://github.com/django-crispy-forms/crispy-bootstrap5/releases
Project-URL: Homepage, https://github.com/django-crispy-forms/crispy-bootstrap5
Project-URL: Issues, https://github.com/django-crispy-forms/crispy-bootstrap5/issues
Classifier: Environment :: Web Environment
Classifier: Framework :: Django
Classifier: Framework :: Django :: 4.2
Classifier: Framework :: Django :: 5.0
Classifier: Framework :: Django :: 5.1
Classifier: License :: OSI Approved :: MIT License
Classifier: Operating System :: OS Independent
Classifier: Programming Language :: Python :: 3 :: Only
Classifier: Programming Language :: Python :: 3.8
Classifier: Programming Language :: Python :: 3.9
Classifier: Programming Language :: Python :: 3.10
Classifier: Programming Language :: Python :: 3.11
Classifier: Programming Language :: Python :: 3.12
Classifier: Topic :: Internet :: WWW/HTTP
Classifier: Topic :: Internet :: WWW/HTTP :: Dynamic Content
Classifier: Topic :: Software Development :: Libraries :: Python Modules
Requires-Python: >=3.8
License-File: LICENSE
Requires-Dist: django>=4.2
Requires-Dist: django-crispy-forms>=2.3
Provides-Extra: test
Requires-Dist: pytest; extra == "test"
Requires-Dist: pytest-django; extra == "test"
